loder/__init__.py
loder/_version.py
loder-0.0.1.dist-info/LICENSE
loder-0.0.1.dist-info/METADATA
loder-0.0.1.dist-info/WHEEL
loder-0.0.1.dist-info/top_level.txt
loder-0.0.1.dist-info/RECORD
